prl/__init__.py
prl/evaluation.py
prl/genF.py
prl/genP.py
prl/prl.py
prl/solvers.py
prl-0.94b0.dist-info/LICENSE
prl-0.94b0.dist-info/METADATA
prl-0.94b0.dist-info/WHEEL
prl-0.94b0.dist-info/top_level.txt
prl-0.94b0.dist-info/RECORD
